src/.example.env
src/__init__.py
src/main.py
src/flows/chat_agent.py
src/flows/should_run_can_error.py
src/flows/should_run_end.py
src/utils/llm.py
src/utils/nodes.py
src/utils/state.py
src/utils/stream.py
src/utils/system.py
src/utils/tools.py
src/utils/vector.py
src/utils/visualize.py
ai_term-0.0.1rc14.dist-info/METADATA
ai_term-0.0.1rc14.dist-info/WHEEL
ai_term-0.0.1rc14.dist-info/entry_points.txt
ai_term-0.0.1rc14.dist-info/top_level.txt
ai_term-0.0.1rc14.dist-info/RECORD
