Metadata-Version: 2.1
Name: ai-term
Version: 0.0.1rc14
Summary: A powerful CLI tool for AI interactions
Home-page: https://github.com/ryaneggz/ai-term
Author: Ryan Eggleston
Author-email: ryaneggleston@promptengineers.ai
Classifier: Development Status :: 3 - Alpha
Classifier: Intended Audience :: Developers
Classifier: License :: OSI Approved :: MIT License
Classifier: Operating System :: OS Independent
Classifier: Programming Language :: Python :: 3.10
Requires-Python: >=3.10
Requires-Dist: python-dotenv
Requires-Dist: langgraph
Requires-Dist: langchain_anthropic
Requires-Dist: langchain_openai
Requires-Dist: langchain-community
Requires-Dist: langchain-experimental
Provides-Extra: dev
Requires-Dist: pytest; extra == "dev"
Requires-Dist: black; extra == "dev"
Requires-Dist: flake8; extra == "dev"
Requires-Dist: twine; extra == "dev"
Requires-Dist: build; extra == "dev"
